covid19_api/__init__.py
covid19_api/src/__init__.py
covid19_api/src/api.py
czech_covid19_data_api-1.0.5.dist-info/METADATA
czech_covid19_data_api-1.0.5.dist-info/WHEEL
czech_covid19_data_api-1.0.5.dist-info/top_level.txt
czech_covid19_data_api-1.0.5.dist-info/RECORD
