Metadata-Version: 2.1
Name: czech-covid19-data-api
Version: 1.0.5
Summary: UNKNOWN
Home-page: https://github.com/radekBednarik/czech-covid19-data-api
Author: Radek 'bednaJedna' Bednarik
Author-email: bednarik.radek@gmail.com
License: UNKNOWN
Keywords: covid19 covid data czech Czechia public api wrapper python python3
Platform: UNKNOWN
Classifier: Programming Language :: Python :: 3
Classifier: License :: OSI Approved :: MIT License
Classifier: Operating System :: OS Independent
Requires-Python: >=3.6
Requires-Dist: requests
